Workbook

Sheet Dashboard
A2: EdTech Implementation Risk Intelligence System (EIRIS)
A3: SEM-Weighted Risk Prioritization Tool | N = 195 Projects | RPI & LA Tech | ARS = P × I × β
B6: Total Projects | E6: Critical + High | H6: High | K6: Moderate | N6: Low
B7: =COUNTA('Risk Register'!A8:A290) -> 195 | E7: =COUNTIF('Risk Register'!J8:J290,"Critical")+COUNTIF('Risk Register'!J8:J290,"High") -> 14 | H7: =COUNTIF('Risk Register'!J8:J290,"High") -> 14 | K7: =COUNTIF('Risk Register'!J8:J290,"Moderate") -> 74 | N7: =COUNTIF('Risk Register'!J8:J290,"Low") -> 107
B10: Current SEM β Weights (Update after AMOS run)
B11: PM → IS β = 0.31 | D11: RM → IS β = 0.53 | F11: PM → RM γ = 0.62
B14: HOW TO USE THIS TOOL
B15: 1 | C15: SEM Weights tab — update β values with final IBM AMOS output. All ARS scores recalculate instantly.
B16: 2 | C16: Risk Register tab — all 195 real projects pre-loaded with live ARS scores, priorities, and recommended actions.
B17: 3 | C17: Add new risks in blank rows at the bottom. Select Category from dropdown; P and I scores auto-pull from your data.
B18: 4 | C18: Risk Heatmap tab — view the ARS matrix showing score ranges for every P × I combination at each β weight.
B19: 5 | C19: Project Analysis tab — filter and review individual project risk profiles sorted by ARS score.
B22: PRIORITY SUMMARY — ALL 195 PROJECTS
B23: Priority | D23: ARS Range | F23: Count (%) | H23: Dominant Pattern | K23: Recommended Response
B24: Critical | D24: ARS > 12 | F24: 0 (0.0%) | H24: — | K24: No Critical risks in current dataset
B25: High | D25: 6.0–12.0 | F25: 28 (14.4%) | H25: All Delayed outcomes; High complexity | K25: Active mitigation required; assign risk owners
B26: Moderate | D26: 3.0–6.0 | F26: 93 (47.7%) | H26: Mix of Delayed and Successful | K26: Periodic monitoring; contingency planning
B27: Low | D27: < 3.0 | F27: 74 (37.9%) | H27: Majority Successful outcomes | K27: Accept with monitoring; review at completion

Sheet Risk Prioritization
A2: Risk Prioritization Center | EIRIS EdTech Implementation Tool
A3: Three tools in one sheet: (1) Score a new project instantly (2) Ranked action plan for High-priority projects (3) Budget allocation across risk tiers
A7: Enter details for any planned EdTech project. ARS score and priority tier calculate automatically from your β weight.
B8: Input Field | C8: Your Entry | E8: Result | F8: Value | H8: Explanation
B9: Project Name | C9: [enter project name] | E9: β Weight (live) | F9: ='SEM Weights'!$D$9 -> 0.38 | H9: Free text — project title
B10: Institution | C10: [enter institution] | E10: P × I | F10: =C14*C15 -> 5 | H10: e.g. RPI, LA Tech, GWU
B11: Risk Category | C11: Risk Management | E11: ARS Score | F11: =C14*C15*'SEM Weights'!$D$9 -> 1.9 | H11: Risk Management / Project Management / Organizational Readiness
B12: PM Principles Used? | C12: Yes | E12: Priority Tier | F12: =IF(F11>12,"CRITICAL",IF(F11>=6,"HIGH",IF(F11>=3,"MODERATE","LOW"))) -> LOW | H12: Yes / No
B14: P — Probability (1–5) | C14: 5 | E14: PM Adjustment | F14: =IF(C12="Yes","PM used — moderate risk reduction expected","No PM — consider adding structured PM practices") -> PM used — moderate risk reduction expected | H14: 1=Very unlikely 3=Possible 5=Almost certain
B15: I — Impact (1–5) | C15: 1 | E15: Peer Comparison | F15: =CONCATENATE("ARS ",TEXT(F11,"0.000")," vs dataset avg ",TEXT(ROUND(3.569,3),"0.000")," and max ",TEXT(ROUND(7.6,3),"0.000")) -> ARS 1.900 vs dataset avg 3.569 and max 7.600 | H15: 1=Negligible 3=Significant 5=Catastrophic
B17: Recommended Action
B18: =IF(F12="CRITICAL","CRITICAL: Stop deployment — assign dedicated risk owner immediately. Convene risk committee.",IF(F12="HIGH","HIGH: Build formal risk register before deployment. Assign risk owner. Develop mitigation plans. Weekly monitoring.",IF(F12="MODERATE","MODERATE: Develop contingency plan by next milestone. Monthly risk reviews. Document lessons learned.","LOW: Proceed with standard monitoring. Log risks at project completion. Review if scope changes."))) -> LOW: Proceed with standard monitoring. Log risks at project completion. Review if scope changes.
A27: TOOL 2 — Ranked Action Plan | High-Priority Projects
A28: Projects ranked by ARS (highest first). All 14 High-priority projects shown with specific mitigation steps. Timeline and owner columns are editable.
A30: Rank | B30: Project ID | C30: Project Name | D30: ARS | E30: Priority | F30: P | G30: I | H30: PM Used?
A31: 1 | B31: P195 | C31: Workday Student | D31: =IFERROR(VLOOKUP(B31,'Risk Register'!$A$8:$I$290,9,FALSE),F31*G31*'SEM Weights'!$D$9) -> 8.113 | E31: =IF(D31>12,"Critical",IF(D31>=6,"High",IF(D31>=3,"Moderate","Low"))) -> High | F31: 4.27 | G31: 5 | H31: Yes
A32: 2 | B32: P053 | C32: Network services | D32: =IFERROR(VLOOKUP(B32,'Risk Register'!$A$8:$I$290,9,FALSE),F32*G32*'SEM Weights'!$D$9) -> 7.4936 | E32: =IF(D32>12,"Critical",IF(D32>=6,"High",IF(D32>=3,"Moderate","Low"))) -> High | F32: 4.64 | G32: 4.25 | H32: Yes
A33: 3 | B33: P107 | C33: Inventions and patents | D33: =IFERROR(VLOOKUP(B33,'Risk Register'!$A$8:$I$290,9,FALSE),F33*G33*'SEM Weights'!$D$9) -> 7.429 | E33: =IF(D33>12,"Critical",IF(D33>=6,"High",IF(D33>=3,"Moderate","Low"))) -> High | F33: 3.91 | G33: 5 | H33: No
A34: 4 | B34: P155 | C34: Email Spam filter | D34: =IFERROR(VLOOKUP(B34,'Risk Register'!$A$8:$I$290,9,FALSE),F34*G34*'SEM Weights'!$D$9) -> 7.3017 | E34: =IF(D34>12,"Critical",IF(D34>=6,"High",IF(D34>=3,"Moderate","Low"))) -> High | F34: 4.27 | G34: 4.5 | H34: Yes
A35: 5 | B35: P049 | C35: Backups | D35: =IFERROR(VLOOKUP(B35,'Risk Register'!$A$8:$I$290,9,FALSE),F35*G35*'SEM Weights'!$D$9) -> 7.05755 | E35: =IF(D35>12,"Critical",IF(D35>=6,"High",IF(D35>=3,"Moderate","Low"))) -> High | F35: 3.91 | G35: 4.75 | H35: Yes
A36: 6 | B36: P010 | C36: Parking Management System | D36: =IFERROR(VLOOKUP(B36,'Risk Register'!$A$8:$I$290,9,FALSE),F36*G36*'SEM Weights'!$D$9) -> 6.89605 | E36: =IF(D36>12,"Critical",IF(D36>=6,"High",IF(D36>=3,"Moderate","Low"))) -> High | F36: 4.27 | G36: 4.25 | H36: No
A37: 7 | B37: P076 | C37: Payment processing Software (check printing) | D37: =IFERROR(VLOOKUP(B37,'Risk Register'!$A$8:$I$290,9,FALSE),F37*G37*'SEM Weights'!$D$9) -> 6.745 | E37: =IF(D37>12,"Critical",IF(D37>=6,"High",IF(D37>=3,"Moderate","Low"))) -> High | F37: 3.55 | G37: 5 | H37: Yes
A38: 8 | B38: P136 | C38: Interlibrary loan and document delivery syst | D38: =IFERROR(VLOOKUP(B38,'Risk Register'!$A$8:$I$290,9,FALSE),F38*G38*'SEM Weights'!$D$9) -> 6.745 | E38: =IF(D38>12,"Critical",IF(D38>=6,"High",IF(D38>=3,"Moderate","Low"))) -> High | F38: 3.55 | G38: 5 | H38: No
A39: 9 | B39: P122 | C39: Package Tracking System | D39: =IFERROR(VLOOKUP(B39,'Risk Register'!$A$8:$I$290,9,FALSE),F39*G39*'SEM Weights'!$D$9) -> 6.745 | E39: =IF(D39>12,"Critical",IF(D39>=6,"High",IF(D39>=3,"Moderate","Low"))) -> High | F39: 3.55 | G39: 5 | H39: Yes
A40: 10 | B40: P142 | C40: Data Warehouse Business Intelligence and Ana | D40: =IFERROR(VLOOKUP(B40,'Risk Register'!$A$8:$I$290,9,FALSE),F40*G40*'SEM Weights'!$D$9) -> 6.6861 | E40: =IF(D40>12,"Critical",IF(D40>=6,"High",IF(D40>=3,"Moderate","Low"))) -> High | F40: 3.91 | G40: 4.5 | H40: Yes
A41: 11 | B41: P110 | C41: Intellectual Property | D41: =IFERROR(VLOOKUP(B41,'Risk Register'!$A$8:$I$290,9,FALSE),F41*G41*'SEM Weights'!$D$9) -> 6.65 | E41: =IF(D41>12,"Critical",IF(D41>=6,"High",IF(D41>=3,"Moderate","Low"))) -> High | F41: 5 | G41: 3.5 | H41: Yes
A42: 12 | B42: P041 | C42: Wireless network management | D42: =IFERROR(VLOOKUP(B42,'Risk Register'!$A$8:$I$290,9,FALSE),F42*G42*'SEM Weights'!$D$9) -> 6.40775 | E42: =IF(D42>12,"Critical",IF(D42>=6,"High",IF(D42>=3,"Moderate","Low"))) -> High | F42: 3.55 | G42: 4.75 | H42: Yes
... A44: 14 | B44: P075 | C44: Alumni collaboration | D44: =IFERROR(VLOOKUP(B44,'Risk Register'!$A$8:$I$290,9,FALSE),F44*G44*'SEM Weights'!$D$9) -> 6.0705 | E44: =IF(D44>12,"Critical",IF(D44>=6,"High",IF(D44>=3,"Moderate","Low"))) -> High | F44: 3.55 | G44: 4.5 | H44: Yes
A47: TOOL 3 — Mitigation Budget Allocation | Enter your total budget
A48: Enter your total mitigation budget. The tool allocates funds across tiers based on ARS-weighted share and recommended per-project minimums.
A50: Total Mitigation Budget ($) | D50: 50000 | E50: ← Enter your budget here
A52: Priority Tier | B52: Projects | C52: Avg ARS | D52: ARS Weight % | E52: Allocated Budget | F52: Per-Project Budget | G52: Min Recommended | H52: Shortfall / Surplus
A53: Critical | B53: =COUNTIF('Risk Register'!$J$8:$J$290,"Critical") -> 0 | C53: =IFERROR(AVERAGEIF('Risk Register'!$J$8:$J$290,"Critical",'Risk Register'!$I$8:$I$290),0) -> 0 | D53: =IF((B53*C53+B54*C54+B55*C55+B56*C56)=0,0,B53*C53/(B53*C53+B54*C54+B55*C55+B56*C56)) -> 0 | E53: =ROUND(D53*$D$50,0) -> 0 | F53: =IFERROR(ROUND(E53/B53,0),0) -> 0 | G53: =B53*15000 -> 0 | H53: =E53-G53 -> 0
A54: High | B54: =COUNTIF('Risk Register'!$J$8:$J$290,"High") -> 14 | C54: =IFERROR(AVERAGEIF('Risk Register'!$J$8:$J$290,"High",'Risk Register'!$I$8:$I$290),0) -> 6.9039214 | D54: =IF((B53*C53+B54*C54+B55*C55+B56*C56)=0,0,B54*C54/(B53*C53+B54*C54+B55*C55+B56*C56)) -> 0.17720948 | E54: =ROUND(D54*$D$50,0) -> 8860 | F54: =IFERROR(ROUND(E54/B54,0),0) -> 633 | G54: =B54*8000 -> 112000 | H54: =E54-G54 -> -103140
A55: Moderate | B55: =COUNTIF('Risk Register'!$J$8:$J$290,"Moderate") -> 74 | C55: =IFERROR(AVERAGEIF('Risk Register'!$J$8:$J$290,"Moderate",'Risk Register'!$I$8:$I$290),0) -> 4.1816946 | D55: =IF((B53*C53+B54*C54+B55*C55+B56*C56)=0,0,B55*C55/(B53*C53+B54*C54+B55*C55+B56*C56)) -> 0.56734485 | E55: =ROUND(D55*$D$50,0) -> 28367 | F55: =IFERROR(ROUND(E55/B55,0),0) -> 383 | G55: =B55*2000 -> 148000 | H55: =E55-G55 -> -119633
A56: Low | B56: =COUNTIF('Risk Register'!$J$8:$J$290,"Low") -> 107 | C56: =IFERROR(AVERAGEIF('Risk Register'!$J$8:$J$290,"Low",'Risk Register'!$I$8:$I$290),0) -> 1.302122 | D56: =IF((B53*C53+B54*C54+B55*C55+B56*C56)=0,0,B56*C56/(B53*C53+B54*C54+B55*C55+B56*C56)) -> 0.25544567 | E56: =ROUND(D56*$D$50,0) -> 12772 | F56: =IFERROR(ROUND(E56/B56,0),0) -> 119 | G56: =B56*500 -> 53500 | H56: =E56-G56 -> -40728
A57: TOTAL | B57: =SUM(B53:B56) -> 195 | D57: =SUM(D53:D56) -> 1 | E57: =SUM(E53:E56) -> 49999 | G57: =SUM(G53:G56) -> 313500 | H57: =SUM(H53:H56) -> -263501
A59: Budget Interpretation
A60: Green surplus = tier is adequately funded at the recommended minimum. Red shortfall = insufficient budget for this tier at minimum recommended levels. If total shortfall is large, prioritise Critical and High tiers first — these directly correspond to projects most likely to be delayed (validated by study data). Modify the budget input cell D above and all allocations recalculate automatically.

Sheet SEM Weights
A2: SEM-Derived Construct Weights — IBM AMOS Output
A3: Blue cells = user inputs. Update β values with your final AMOS path coefficients. All ARS calculations in the Risk Register update automatically.
B5: ⚠ Placeholder β values shown. Replace with actual AMOS standardized path coefficients after running your SEM.
B7: Construct | C7: Path | D7: β Coefficient | E7: Std. Error | F7: t-value | G7: p-value | H7: 95% CI | I7: Supported?
B8: Project Management (PM) | C8: PM → IS (Direct) | D8: 0.143 | E8: 0.07 | F8: 4.43 | G8: < 0.001 | H8: [0.17, 0.45] | I8: Yes
B9: Risk Management (RM) | C9: RM → IS (Direct) | D9: 0.38 | E9: 0.08 | F9: 5.5 | G9: < 0.001 | H9: [0.28, 0.60] | I9: Yes
B10: PM (Mediated) | C10: PM → RM → IS | D10: 0.27 | E10: 0.06 | F10: 4.5 | G10: < 0.001 | H10: [0.15, 0.41] | I10: Yes
B11: Project Management | C11: PM → RM | D11: 0.62 | E11: 0.09 | F11: 6.89 | G11: < 0.001 | H11: [0.53, 0.80] | I11: Yes
B15: WEIGHTS APPLIED IN ARS FORMULA — PULL FROM ABOVE
B16: PM-category risks (β = PM → IS) | F16: ='SEM Weights'!D8 -> 0.143 | G16: Used as weight for all Project Management risks in register
B17: RM-category risks (β = RM → IS) | F17: ='SEM Weights'!D9 -> 0.38 | G17: Used as weight for all Risk Management risks in register — THIS IS YOUR ARS β

Sheet Risk Register
A2: Risk Register — All 195 EdTech Projects | ARS-Weighted Priorities
A3: ARS = P × I × β | β weights live from SEM Weights sheet | Sorted by ARS (highest first) | Blue cells = user inputs
A5: Total | B5: Critical | C5: High | D5: Moderate | E5: Low | F5: Avg ARS
A6: =COUNTA(A8:A290)-COUNTBLANK(A8:A290) -> 107 | B6: =COUNTIF(J8:J290,"Critical") -> 0 | C6: =COUNTIF(J8:J290,"High") -> 14 | D6: =COUNTIF(J8:J290,"Moderate") -> 74 | E6: =COUNTIF(J8:J290,"Low") -> 107 | F6: =ROUND(AVERAGE(I8:I290),3) -> 2.797
A7: Project ID | B7: Institution | C7: Project Name | D7: Risk Category | E7: P (Prob) 1–5 | F7: I (Impact) 1–5 | G7: β Weight (SEM) | H7: P × I | I7: ARS (P×I×β) | J7: Priority Tier | K7: Recommended Action | L7: PM Used | M7: Outcome
A8: P195 | B8: LA Tech | C8: Workday Student | D8: Risk Management | E8: 4.27 | F8: 5 | G8: =IF(D8="Project Management",'SEM Weights'!$D$8,'SEM Weights'!$D$9) -> 0.38 | H8: =E8*F8 -> 21.35 | I8: =E8*F8*G8 -> 8.113 | J8: =IF(I8="","",IF(I8>12,"Critical",IF(I8>=6,"High",IF(I8>=3,"Moderate","Low")))) -> High | K8: =IF(J8="Critical","Immediate mitigation — assign dedicated risk owner now",IF(J8="High","Active mitigation planning required; include in project risk register",IF(J8="Moderate","Periodic monitoring; develop contingency plan at next milestone",IF(J8="Low","Accept with monitoring; review at project completion","")))) -> Active mitigation planning required; include in project risk register | L8: Yes | M8: Delayed
A9: P053 | B9: RPI | C9: Network services | D9: Risk Management | E9: 4.64 | F9: 4.25 | G9: =IF(D9="Project Management",'SEM Weights'!$D$8,'SEM Weights'!$D$9) -> 0.38 | H9: =E9*F9 -> 19.72 | I9: =E9*F9*G9 -> 7.4936 | J9: =IF(I9="","",IF(I9>12,"Critical",IF(I9>=6,"High",IF(I9>=3,"Moderate","Low")))) -> High | K9: =IF(J9="Critical","Immediate mitigation — assign dedicated risk owner now",IF(J9="High","Active mitigation planning required; include in project risk register",IF(J9="Moderate","Periodic monitoring; develop contingency plan at next milestone",IF(J9="Low","Accept with monitoring; review at project completion","")))) -> Active mitigation planning required; include in project risk register | L9: Yes | M9: Delayed
A10: P107 | B10: RPI | C10: Inventions and patents | D10: Risk Management | E10: 3.91 | F10: 5 | G10: =IF(D10="Project Management",'SEM Weights'!$D$8,'SEM Weights'!$D$9) -> 0.38 | H10: =E10*F10 -> 19.55 | I10: =E10*F10*G10 -> 7.429 | J10: =IF(I10="","",IF(I10>12,"Critical",IF(I10>=6,"High",IF(I10>=3,"Moderate","Low")))) -> High | K10: =IF(J10="Critical","Immediate mitigation — assign dedicated risk owner now",IF(J10="High","Active mitigation planning required; include in project risk register",IF(J10="Moderate","Periodic monitoring; develop contingency plan at next milestone",IF(J10="Low","Accept with monitoring; review at project completion","")))) -> Active mitigation planning required; include in project risk register | L10: No | M10: Delayed
A11: P155 | B11: RPI | C11: Email Spam filter | D11: Risk Management | E11: 4.27 | F11: 4.5 | G11: =IF(D11="Project Management",'SEM Weights'!$D$8,'SEM Weights'!$D$9) -> 0.38 | H11: =E11*F11 -> 19.215 | I11: =E11*F11*G11 -> 7.3017 | J11: =IF(I11="","",IF(I11>12,"Critical",IF(I11>=6,"High",IF(I11>=3,"Moderate","Low")))) -> High | K11: =IF(J11="Critical","Immediate mitigation — assign dedicated risk owner now",IF(J11="High","Active mitigation planning required; include in project risk register",IF(J11="Moderate","Periodic monitoring; develop contingency plan at next milestone",IF(J11="Low","Accept with monitoring; review at project completion","")))) -> Active mitigation planning required; include in project risk register | L11: Yes | M11: Delayed
A12: P049 | B12: RPI | C12: Backups | D12: Risk Management | E12: 3.91 | F12: 4.75 | G12: =IF(D12="Project Management",'SEM Weights'!$D$8,'SEM Weights'!$D$9) -> 0.38 | H12: =E12*F12 -> 18.5725 | I12: =E12*F12*G12 -> 7.05755 | J12: =IF(I12="","",IF(I12>12,"Critical",IF(I12>=6,"High",IF(I12>=3,"Moderate","Low")))) -> High | K12: =IF(J12="Critical","Immediate mitigation — assign dedicated risk owner now",IF(J12="High","Active mitigation planning required; include in project risk register",IF(J12="Moderate","Periodic monitoring; develop contingency plan at next milestone",IF(J12="Low","Accept with monitoring; review at project completion","")))) -> Active mitigation planning required; include in project risk register | L12: Yes | M12: Delayed
A13: P010 | B13: RPI | C13: Parking Management System | D13: Risk Management | E13: 4.27 | F13: 4.25 | G13: =IF(D13="Project Management",'SEM Weights'!$D$8,'SEM Weights'!$D$9) -> 0.38 | H13: =E13*F13 -> 18.1475 | I13: =E13*F13*G13 -> 6.89605 | J13: =IF(I13="","",IF(I13>12,"Critical",IF(I13>=6,"High",IF(I13>=3,"Moderate","Low")))) -> High | K13: =IF(J13="Critical","Immediate mitigation — assign dedicated risk owner now",IF(J13="High","Active mitigation planning required; include in project risk register",IF(J13="Moderate","Periodic monitoring; develop contingency plan at next milestone",IF(J13="Low","Accept with monitoring; review at project completion","")))) -> Active mitigation planning required; include in project risk register | L13: No | M13: Delayed
A14: P076 | B14: RPI | C14: Payment processing Software (check printing) | D14: Risk Management | E14: 3.55 | F14: 5 | G14: =IF(D14="Project Management",'SEM Weights'!$D$8,'SEM Weights'!$D$9) -> 0.38 | H14: =E14*F14 -> 17.75 | I14: =E14*F14*G14 -> 6.745 | J14: =IF(I14="","",IF(I14>12,"Critical",IF(I14>=6,"High",IF(I14>=3,"Moderate","Low")))) -> High | K14: =IF(J14="Critical","Immediate mitigation — assign dedicated risk owner now",IF(J14="High","Active mitigation planning required; include in project risk register",IF(J14="Moderate","Periodic monitoring; develop contingency plan at next milestone",IF(J14="Low","Accept with monitoring; review at project completion","")))) -> Active mitigation planning required; include in project risk register | L14: Yes | M14: Delayed
A15: P136 | B15: RPI | C15: Interlibrary loan and document delivery syste | D15: Risk Management | E15: 3.55 | F15: 5 | G15: =IF(D15="Project Management",'SEM Weights'!$D$8,'SEM Weights'!$D$9) -> 0.38 | H15: =E15*F15 -> 17.75 | I15: =E15*F15*G15 -> 6.745 | J15: =IF(I15="","",IF(I15>12,"Critical",IF(I15>=6,"High",IF(I15>=3,"Moderate","Low")))) -> High | K15: =IF(J15="Critical","Immediate mitigation — assign dedicated risk owner now",IF(J15="High","Active mitigation planning required; include in project risk register",IF(J15="Moderate","Periodic monitoring; develop contingency plan at next milestone",IF(J15="Low","Accept with monitoring; review at project completion","")))) -> Active mitigation planning required; include in project risk register | L15: No | M15: Delayed
A16: P122 | B16: RPI | C16: Package Tracking System | D16: Risk Management | E16: 3.55 | F16: 5 | G16: =IF(D16="Project Management",'SEM Weights'!$D$8,'SEM Weights'!$D$9) -> 0.38 | H16: =E16*F16 -> 17.75 | I16: =E16*F16*G16 -> 6.745 | J16: =IF(I16="","",IF(I16>12,"Critical",IF(I16>=6,"High",IF(I16>=3,"Moderate","Low")))) -> High | K16: =IF(J16="Critical","Immediate mitigation — assign dedicated risk owner now",IF(J16="High","Active mitigation planning required; include in project risk register",IF(J16="Moderate","Periodic monitoring; develop contingency plan at next milestone",IF(J16="Low","Accept with monitoring; review at project completion","")))) -> Active mitigation planning required; include in project risk register | L16: Yes | M16: Delayed
A17: P142 | B17: RPI | C17: Data Warehouse Business Intelligence and Anal | D17: Risk Management | E17: 3.91 | F17: 4.5 | G17: =IF(D17="Project Management",'SEM Weights'!$D$8,'SEM Weights'!$D$9) -> 0.38 | H17: =E17*F17 -> 17.595 | I17: =E17*F17*G17 -> 6.6861 | J17: =IF(I17="","",IF(I17>12,"Critical",IF(I17>=6,"High",IF(I17>=3,"Moderate","Low")))) -> High | K17: =IF(J17="Critical","Immediate mitigation — assign dedicated risk owner now",IF(J17="High","Active mitigation planning required; include in project risk register",IF(J17="Moderate","Periodic monitoring; develop contingency plan at next milestone",IF(J17="Low","Accept with monitoring; review at project completion","")))) -> Active mitigation planning required; include in project risk register | L17: Yes | M17: Delayed
A18: P110 | B18: RPI | C18: Intellectual Property | D18: Risk Management | E18: 5 | F18: 3.5 | G18: =IF(D18="Project Management",'SEM Weights'!$D$8,'SEM Weights'!$D$9) -> 0.38 | H18: =E18*F18 -> 17.5 | I18: =E18*F18*G18 -> 6.65 | J18: =IF(I18="","",IF(I18>12,"Critical",IF(I18>=6,"High",IF(I18>=3,"Moderate","Low")))) -> High | K18: =IF(J18="Critical","Immediate mitigation — assign dedicated risk owner now",IF(J18="High","Active mitigation planning required; include in project risk register",IF(J18="Moderate","Periodic monitoring; develop contingency plan at next milestone",IF(J18="Low","Accept with monitoring; review at project completion","")))) -> Active mitigation planning required; include in project risk register | L18: Yes | M18: Failed
A19: P041 | B19: RPI | C19: Wireless network management | D19: Risk Management | E19: 3.55 | F19: 4.75 | G19: =IF(D19="Project Management",'SEM Weights'!$D$8,'SEM Weights'!$D$9) -> 0.38 | H19: =E19*F19 -> 16.8625 | I19: =E19*F19*G19 -> 6.40775 | J19: =IF(I19="","",IF(I19>12,"Critical",IF(I19>=6,"High",IF(I19>=3,"Moderate","Low")))) -> High | K19: =IF(J19="Critical","Immediate mitigation — assign dedicated risk owner now",IF(J19="High","Active mitigation planning required; include in project risk register",IF(J19="Moderate","Periodic monitoring; develop contingency plan at next milestone",IF(J19="Low","Accept with monitoring; review at project completion","")))) -> Active mitigation planning required; include in project risk register | L19: Yes | M19: Delayed
... A85: P187 | B85: RPI | C85: Chemical Tracking System | D85: Organizational Readiness | E85: 2.09 | F85: 4.25 | G85: =IF(D85="Project Management",'SEM Weights'!$D$8,'SEM Weights'!$D$9) -> 0.38 | H85: =E85*F85 -> 8.8825 | I85: =E85*F85*G85 -> 3.37535 | J85: =IF(I85="","",IF(I85>12,"Critical",IF(I85>=6,"High",IF(I85>=3,"Moderate","Low")))) -> Moderate | K85: =IF(J85="Critical","Immediate mitigation — assign dedicated risk owner now",IF(J85="High","Active mitigation planning required; include in project risk register",IF(J85="Moderate","Periodic monitoring; develop contingency plan at next milestone",IF(J85="Low","Accept with monitoring; review at project completion","")))) -> Periodic monitoring; develop contingency plan at next milestone | L85: Yes | M85: Successful
A86: P081 | B86: RPI | D86: Risk Management | E86: 3.55 | F86: 2.5 | G86: =IF(D86="Project Management",'SEM Weights'!$D$8,'SEM Weights'!$D$9) -> 0.38 | H86: =E86*F86 -> 8.875 | I86: =E86*F86*G86 -> 3.3725 | J86: =IF(I86="","",IF(I86>12,"Critical",IF(I86>=6,"High",IF(I86>=3,"Moderate","Low")))) -> Moderate | K86: =IF(J86="Critical","Immediate mitigation — assign dedicated risk owner now",IF(J86="High","Active mitigation planning required; include in project risk register",IF(J86="Moderate","Periodic monitoring; develop contingency plan at next milestone",IF(J86="Low","Accept with monitoring; review at project completion","")))) -> Periodic monitoring; develop contingency plan at next milestone | L86: Yes | M86: Delayed
A87: P021 | B87: RPI | C87: Public Safety Voice Recording System | D87: Risk Management | E87: 3.55 | F87: 2.5 | G87: =IF(D87="Project Management",'SEM Weights'!$D$8,'SEM Weights'!$D$9) -> 0.38 | H87: =E87*F87 -> 8.875 | I87: =E87*F87*G87 -> 3.3725 | J87: =IF(I87="","",IF(I87>12,"Critical",IF(I87>=6,"High",IF(I87>=3,"Moderate","Low")))) -> Moderate | K87: =IF(J87="Critical","Immediate mitigation — assign dedicated risk owner now",IF(J87="High","Active mitigation planning required; include in project risk register",IF(J87="Moderate","Periodic monitoring; develop contingency plan at next milestone",IF(J87="Low","Accept with monitoring; review at project completion","")))) -> Periodic monitoring; develop contingency plan at next milestone | L87: Yes | M87: Delayed
A88: P105 | B88: RPI | C88: Space Management | D88: Risk Management | E88: 3.55 | F88: 2.5 | G88: =IF(D88="Project Management",'SEM Weights'!$D$8,'SEM Weights'!$D$9) -> 0.38 | H88: =E88*F88 -> 8.875 | I88: =E88*F88*G88 -> 3.3725 | J88: =IF(I88="","",IF(I88>12,"Critical",IF(I88>=6,"High",IF(I88>=3,"Moderate","Low")))) -> Moderate | K88: =IF(J88="Critical","Immediate mitigation — assign dedicated risk owner now",IF(J88="High","Active mitigation planning required; include in project risk register",IF(J88="Moderate","Periodic monitoring; develop contingency plan at next milestone",IF(J88="Low","Accept with monitoring; review at project completion","")))) -> Periodic monitoring; develop contingency plan at next milestone | L88: Yes | M88: Delayed
A89: P147 | B89: RPI | C89: Postal System | D89: Risk Management | E89: 3.55 | F89: 2.5 | G89: =IF(D89="Project Management",'SEM Weights'!$D$8,'SEM Weights'!$D$9) -> 0.38 | H89: =E89*F89 -> 8.875 | I89: =E89*F89*G89 -> 3.3725 | J89: =IF(I89="","",IF(I89>12,"Critical",IF(I89>=6,"High",IF(I89>=3,"Moderate","Low")))) -> Moderate | K89: =IF(J89="Critical","Immediate mitigation — assign dedicated risk owner now",IF(J89="High","Active mitigation planning required; include in project risk register",IF(J89="Moderate","Periodic monitoring; develop contingency plan at next milestone",IF(J89="Low","Accept with monitoring; review at project completion","")))) -> Periodic monitoring; develop contingency plan at next milestone | L89: No | M89: Delayed
A90: P082 | B90: RPI | C90: View/Purchase course materials from the LMS V | D90: Risk Management | E90: 3.91 | F90: 2.25 | G90: =IF(D90="Project Management",'SEM Weights'!$D$8,'SEM Weights'!$D$9) -> 0.38 | H90: =E90*F90 -> 8.7975 | I90: =E90*F90*G90 -> 3.34305 | J90: =IF(I90="","",IF(I90>12,"Critical",IF(I90>=6,"High",IF(I90>=3,"Moderate","Low")))) -> Moderate | K90: =IF(J90="Critical","Immediate mitigation — assign dedicated risk owner now",IF(J90="High","Active mitigation planning required; include in project risk register",IF(J90="Moderate","Periodic monitoring; develop contingency plan at next milestone",IF(J90="Low","Accept with monitoring; review at project completion","")))) -> Periodic monitoring; develop contingency plan at next milestone | L90: No | M90: Delayed
A91: P138 | B91: RPI | C91: Card Access ID Access; Campus Security – door | D91: Organizational Readiness | E91: 3.18 | F91: 2.75 | G91: =IF(D91="Project Management",'SEM Weights'!$D$8,'SEM Weights'!$D$9) -> 0.38 | H91: =E91*F91 -> 8.745 | I91: =E91*F91*G91 -> 3.3231 | J91: =IF(I91="","",IF(I91>12,"Critical",IF(I91>=6,"High",IF(I91>=3,"Moderate","Low")))) -> Moderate | K91: =IF(J91="Critical","Immediate mitigation — assign dedicated risk owner now",IF(J91="High","Active mitigation planning required; include in project risk register",IF(J91="Moderate","Periodic monitoring; develop contingency plan at next milestone",IF(J91="Low","Accept with monitoring; review at project completion","")))) -> Periodic monitoring; develop contingency plan at next milestone | L91: No | M91: Delayed
A92: P184 | B92: RPI | C92: Online meal ordering system | D92: Organizational Readiness | E92: 3.18 | F92: 2.75 | G92: =IF(D92="Project Management",'SEM Weights'!$D$8,'SEM Weights'!$D$9) -> 0.38 | H92: =E92*F92 -> 8.745 | I92: =E92*F92*G92 -> 3.3231 | J92: =IF(I92="","",IF(I92>12,"Critical",IF(I92>=6,"High",IF(I92>=3,"Moderate","Low")))) -> Moderate | K92: =IF(J92="Critical","Immediate mitigation — assign dedicated risk owner now",IF(J92="High","Active mitigation planning required; include in project risk register",IF(J92="Moderate","Periodic monitoring; develop contingency plan at next milestone",IF(J92="Low","Accept with monitoring; review at project completion","")))) -> Periodic monitoring; develop contingency plan at next milestone | L92: Yes | M92: Delayed
A93: P084 | B93: RPI | C93: View course material from the course catalog | D93: Organizational Readiness | E93: 3.18 | F93: 2.75 | G93: =IF(D93="Project Management",'SEM Weights'!$D$8,'SEM Weights'!$D$9) -> 0.38 | H93: =E93*F93 -> 8.745 | I93: =E93*F93*G93 -> 3.3231 | J93: =IF(I93="","",IF(I93>12,"Critical",IF(I93>=6,"High",IF(I93>=3,"Moderate","Low")))) -> Moderate | K93: =IF(J93="Critical","Immediate mitigation — assign dedicated risk owner now",IF(J93="High","Active mitigation planning required; include in project risk register",IF(J93="Moderate","Periodic monitoring; develop contingency plan at next milestone",IF(J93="Low","Accept with monitoring; review at project completion","")))) -> Periodic monitoring; develop contingency plan at next milestone | L93: Yes | M93: Delayed
A94: P028 | B94: RPI | C94: LMS (Learning Mgmt System) | D94: Organizational Readiness | E94: 3.18 | F94: 2.75 | G94: =IF(D94="Project Management",'SEM Weights'!$D$8,'SEM Weights'!$D$9) -> 0.38 | H94: =E94*F94 -> 8.745 | I94: =E94*F94*G94 -> 3.3231 | J94: =IF(I94="","",IF(I94>12,"Critical",IF(I94>=6,"High",IF(I94>=3,"Moderate","Low")))) -> Moderate | K94: =IF(J94="Critical","Immediate mitigation — assign dedicated risk owner now",IF(J94="High","Active mitigation planning required; include in project risk register",IF(J94="Moderate","Periodic monitoring; develop contingency plan at next milestone",IF(J94="Low","Accept with monitoring; review at project completion","")))) -> Periodic monitoring; develop contingency plan at next milestone | L94: No | M94: Delayed
A95: P079 | B95: RPI | C95: Load Balancing | D95: Organizational Readiness | E95: 3.18 | F95: 2.75 | G95: =IF(D95="Project Management",'SEM Weights'!$D$8,'SEM Weights'!$D$9) -> 0.38 | H95: =E95*F95 -> 8.745 | I95: =E95*F95*G95 -> 3.3231 | J95: =IF(I95="","",IF(I95>12,"Critical",IF(I95>=6,"High",IF(I95>=3,"Moderate","Low")))) -> Moderate | K95: =IF(J95="Critical","Immediate mitigation — assign dedicated risk owner now",IF(J95="High","Active mitigation planning required; include in project risk register",IF(J95="Moderate","Periodic monitoring; develop contingency plan at next milestone",IF(J95="Low","Accept with monitoring; review at project completion","")))) -> Periodic monitoring; develop contingency plan at next milestone | L95: Yes | M95: Delayed
A96: P120 | B96: RPI | C96: Institutional Research compliance management | D96: Organizational Readiness | E96: 3.18 | F96: 2.75 | G96: =IF(D96="Project Management",'SEM Weights'!$D$8,'SEM Weights'!$D$9) -> 0.38 | H96: =E96*F96 -> 8.745 | I96: =E96*F96*G96 -> 3.3231 | J96: =IF(I96="","",IF(I96>12,"Critical",IF(I96>=6,"High",IF(I96>=3,"Moderate","Low")))) -> Moderate | K96: =IF(J96="Critical","Immediate mitigation — assign dedicated risk owner now",IF(J96="High","Active mitigation planning required; include in project risk register",IF(J96="Moderate","Periodic monitoring; develop contingency plan at next milestone",IF(J96="Low","Accept with monitoring; review at project completion","")))) -> Periodic monitoring; develop contingency plan at next milestone | L96: Yes | M96: Delayed
A97: P080 | B97: RPI | C97: Process Management | D97: Organizational Readiness | E97: 3.18 | F97: 2.75 | G97: =IF(D97="Project Management",'SEM Weights'!$D$8,'SEM Weights'!$D$9) -> 0.38 | H97: =E97*F97 -> 8.745 | I97: =E97*F97*G97 -> 3.3231 | J97: =IF(I97="","",IF(I97>12,"Critical",IF(I97>=6,"High",IF(I97>=3,"Moderate","Low")))) -> Moderate | K97: =IF(J97="Critical","Immediate mitigation — assign dedicated risk owner now",IF(J97="High","Active mitigation planning required; include in project risk register",IF(J97="Moderate","Periodic monitoring; develop contingency plan at next milestone",IF(J97="Low","Accept with monitoring; review at project completion","")))) -> Periodic monitoring; develop contingency plan at next milestone | L97: Yes | M97: Delayed
A98: P185 | B98: RPI | C98: Project management tool | D98: Organizational Readiness | E98: 2.45 | F98: 3.5 | G98: =IF(D98="Project Management",'SEM Weights'!$D$8,'SEM Weights'!$D$9) -> 0.38 | H98: =E98*F98 -> 8.575 | I98: =E98*F98*G98 -> 3.2585 | J98: =IF(I98="","",IF(I98>12,"Critical",IF(I98>=6,"High",IF(I98>=3,"Moderate","Low")))) -> Moderate | K98: =IF(J98="Critical","Immediate mitigation — assign dedicated risk owner now",IF(J98="High","Active mitigation planning required; include in project risk register",IF(J98="Moderate","Periodic monitoring; develop contingency plan at next milestone",IF(J98="Low","Accept with monitoring; review at project completion","")))) -> Periodic monitoring; develop contingency plan at next milestone | L98: Yes | M98: Successful
... A198: P047 | B198: RPI | C198: Student Government system for club budgeting | D198: Project Management | E198: 2.09 | F198: 1 | G198: =IF(D198="Project Management",'SEM Weights'!$D$8,'SEM Weights'!$D$9) -> 0.143 | H198: =E198*F198 -> 2.09 | I198: =E198*F198*G198 -> 0.29887 | J198: =IF(I198="","",IF(I198>12,"Critical",IF(I198>=6,"High",IF(I198>=3,"Moderate","Low")))) -> Low | K198: =IF(J198="Critical","Immediate mitigation — assign dedicated risk owner now",IF(J198="High","Active mitigation planning required; include in project risk register",IF(J198="Moderate","Periodic monitoring; develop contingency plan at next milestone",IF(J198="Low","Accept with monitoring; review at project completion","")))) -> Accept with monitoring; review at project completion | L198: Yes | M198: Successful
A199: P093 | B199: RPI | D199: Project Management | E199: 2.09 | F199: 1 | G199: =IF(D199="Project Management",'SEM Weights'!$D$8,'SEM Weights'!$D$9) -> 0.143 | H199: =E199*F199 -> 2.09 | I199: =E199*F199*G199 -> 0.29887 | J199: =IF(I199="","",IF(I199>12,"Critical",IF(I199>=6,"High",IF(I199>=3,"Moderate","Low")))) -> Low | K199: =IF(J199="Critical","Immediate mitigation — assign dedicated risk owner now",IF(J199="High","Active mitigation planning required; include in project risk register",IF(J199="Moderate","Periodic monitoring; develop contingency plan at next milestone",IF(J199="Low","Accept with monitoring; review at project completion","")))) -> Accept with monitoring; review at project completion | L199: Yes | M199: Successful
A200: P146 | B200: RPI | C200: Print job management/accounting | D200: Project Management | E200: 1.36 | F200: 1.5 | G200: =IF(D200="Project Management",'SEM Weights'!$D$8,'SEM Weights'!$D$9) -> 0.143 | H200: =E200*F200 -> 2.04 | I200: =E200*F200*G200 -> 0.29172 | J200: =IF(I200="","",IF(I200>12,"Critical",IF(I200>=6,"High",IF(I200>=3,"Moderate","Low")))) -> Low | K200: =IF(J200="Critical","Immediate mitigation — assign dedicated risk owner now",IF(J200="High","Active mitigation planning required; include in project risk register",IF(J200="Moderate","Periodic monitoring; develop contingency plan at next milestone",IF(J200="Low","Accept with monitoring; review at project completion","")))) -> Accept with monitoring; review at project completion | L200: No | M200: Successful
A201: P156 | B201: RPI | C201: Development call campaign, RenExchange | D201: Project Management | E201: 1.36 | F201: 1.5 | G201: =IF(D201="Project Management",'SEM Weights'!$D$8,'SEM Weights'!$D$9) -> 0.143 | H201: =E201*F201 -> 2.04 | I201: =E201*F201*G201 -> 0.29172 | J201: =IF(I201="","",IF(I201>12,"Critical",IF(I201>=6,"High",IF(I201>=3,"Moderate","Low")))) -> Low | K201: =IF(J201="Critical","Immediate mitigation — assign dedicated risk owner now",IF(J201="High","Active mitigation planning required; include in project risk register",IF(J201="Moderate","Periodic monitoring; develop contingency plan at next milestone",IF(J201="Low","Accept with monitoring; review at project completion","")))) -> Accept with monitoring; review at project completion | L201: No | M201: Successful
A202: P176 | B202: RPI | C202: Budget Planning | D202: Project Management | E202: 1 | F202: 1.75 | G202: =IF(D202="Project Management",'SEM Weights'!$D$8,'SEM Weights'!$D$9) -> 0.143 | H202: =E202*F202 -> 1.75 | I202: =E202*F202*G202 -> 0.25025 | J202: =IF(I202="","",IF(I202>12,"Critical",IF(I202>=6,"High",IF(I202>=3,"Moderate","Low")))) -> Low | K202: =IF(J202="Critical","Immediate mitigation — assign dedicated risk owner now",IF(J202="High","Active mitigation planning required; include in project risk register",IF(J202="Moderate","Periodic monitoring; develop contingency plan at next milestone",IF(J202="Low","Accept with monitoring; review at project completion","")))) -> Accept with monitoring; review at project completion | L202: Yes | M202: Successful

Sheet Risk Heatmap
A2: Risk Heatmap — ARS Matrix by P × I × β
A3: Each cell = ARS value for that P × I combination at the given β weight. Colour = priority tier. Your dataset β = 0.53 (RM) and 0.31 (PM).
B6: =CONCATENATE("PM Risks — β = ",TEXT('SEM Weights'!$D$8,"0.000")," (from SEM Weights D8)") -> PM Risks — β = 0.143 (from SEM Weights D8) | K6: =CONCATENATE("RM Risks — β = ",TEXT('SEM Weights'!$D$9,"0.000")," (from SEM Weights D9)") -> RM Risks — β = 0.380 (from SEM Weights D9)
B7: P \ I → | C7: I = 1 | D7: I = 2 | E7: I = 3 | F7: I = 4 | G7: I = 5 | H7: Max ARS | K7: P \ I → | L7: I = 1 | M7: I = 2 | N7: I = 3 | O7: I = 4 | P7: I = 5 | Q7: Max ARS
B8: P = 5 | C8: =5*1*'SEM Weights'!$D$8 -> 0.715 | D8: =5*2*'SEM Weights'!$D$8 -> 1.43 | E8: =5*3*'SEM Weights'!$D$8 -> 2.145 | F8: =5*4*'SEM Weights'!$D$8 -> 2.86 | G8: =5*5*'SEM Weights'!$D$8 -> 3.575 | H8: =5*5*'SEM Weights'!$D$8 -> 3.575 | K8: P = 5 | L8: =5*1*'SEM Weights'!$D$9 -> 1.9 | M8: =5*2*'SEM Weights'!$D$9 -> 3.8 | N8: =5*3*'SEM Weights'!$D$9 -> 5.7 | O8: =5*4*'SEM Weights'!$D$9 -> 7.6 | P8: =5*5*'SEM Weights'!$D$9 -> 9.5 | Q8: =5*5*'SEM Weights'!$D$9 -> 9.5
B9: P = 4 | C9: =4*1*'SEM Weights'!$D$8 -> 0.572 | D9: =4*2*'SEM Weights'!$D$8 -> 1.144 | E9: =4*3*'SEM Weights'!$D$8 -> 1.716 | F9: =4*4*'SEM Weights'!$D$8 -> 2.288 | G9: =4*5*'SEM Weights'!$D$8 -> 2.86 | H9: =4*5*'SEM Weights'!$D$8 -> 2.86 | K9: P = 4 | L9: =4*1*'SEM Weights'!$D$9 -> 1.52 | M9: =4*2*'SEM Weights'!$D$9 -> 3.04 | N9: =4*3*'SEM Weights'!$D$9 -> 4.56 | O9: =4*4*'SEM Weights'!$D$9 -> 6.08 | P9: =4*5*'SEM Weights'!$D$9 -> 7.6 | Q9: =4*5*'SEM Weights'!$D$9 -> 7.6
B10: P = 3 | C10: =3*1*'SEM Weights'!$D$8 -> 0.429 | D10: =3*2*'SEM Weights'!$D$8 -> 0.858 | E10: =3*3*'SEM Weights'!$D$8 -> 1.287 | F10: =3*4*'SEM Weights'!$D$8 -> 1.716 | G10: =3*5*'SEM Weights'!$D$8 -> 2.145 | H10: =3*5*'SEM Weights'!$D$8 -> 2.145 | K10: P = 3 | L10: =3*1*'SEM Weights'!$D$9 -> 1.14 | M10: =3*2*'SEM Weights'!$D$9 -> 2.28 | N10: =3*3*'SEM Weights'!$D$9 -> 3.42 | O10: =3*4*'SEM Weights'!$D$9 -> 4.56 | P10: =3*5*'SEM Weights'!$D$9 -> 5.7 | Q10: =3*5*'SEM Weights'!$D$9 -> 5.7
B11: P = 2 | C11: =2*1*'SEM Weights'!$D$8 -> 0.286 | D11: =2*2*'SEM Weights'!$D$8 -> 0.572 | E11: =2*3*'SEM Weights'!$D$8 -> 0.858 | F11: =2*4*'SEM Weights'!$D$8 -> 1.144 | G11: =2*5*'SEM Weights'!$D$8 -> 1.43 | H11: =2*5*'SEM Weights'!$D$8 -> 1.43 | K11: P = 2 | L11: =2*1*'SEM Weights'!$D$9 -> 0.76 | M11: =2*2*'SEM Weights'!$D$9 -> 1.52 | N11: =2*3*'SEM Weights'!$D$9 -> 2.28 | O11: =2*4*'SEM Weights'!$D$9 -> 3.04 | P11: =2*5*'SEM Weights'!$D$9 -> 3.8 | Q11: =2*5*'SEM Weights'!$D$9 -> 3.8
B12: P = 1 | C12: =1*1*'SEM Weights'!$D$8 -> 0.143 | D12: =1*2*'SEM Weights'!$D$8 -> 0.286 | E12: =1*3*'SEM Weights'!$D$8 -> 0.429 | F12: =1*4*'SEM Weights'!$D$8 -> 0.572 | G12: =1*5*'SEM Weights'!$D$8 -> 0.715 | H12: =1*5*'SEM Weights'!$D$8 -> 0.715 | K12: P = 1 | L12: =1*1*'SEM Weights'!$D$9 -> 0.38 | M12: =1*2*'SEM Weights'!$D$9 -> 0.76 | N12: =1*3*'SEM Weights'!$D$9 -> 1.14 | O12: =1*4*'SEM Weights'!$D$9 -> 1.52 | P12: =1*5*'SEM Weights'!$D$9 -> 1.9 | Q12: =1*5*'SEM Weights'!$D$9 -> 1.9
B15: ACTUAL ARS DISTRIBUTION IN DATASET (N = 195)
B16: High (ARS 6–12): 28 projects (14.4%) | D16: Moderate (3–6): 93 projects (47.7%) | F16: Low (< 3): 74 projects (37.9%) | H16: Max ARS in data: 9.394 (P195 — Workday Student, LA Tech) | J16: Mean ARS: 3.805
B19: LEGEND
B20: Critical | D20: ARS > 12 | F20: No projects in current dataset at this tier
B21: High | D21: 6.0–12.0 | F21: 28 projects (14.4%) — all Delayed; assign risk owners now
B22: Moderate | D22: 3.0–6.0 | F22: 93 projects (47.7%) — active monitoring and contingency planning
B23: Low | D23: < 3.0 | F23: 74 projects (37.9%) — majority Successful; accept with monitoring

Sheet Project Analysis
A2: Project Analysis — Top 30 Highest ARS Projects
A3: Projects sorted by ARS score (highest risk first). Use this sheet to identify which projects need immediate attention.
A5: Rank | B5: Project ID | C5: Institution | D5: Project Name | E5: Category | F5: P | G5: I | H5: β | I5: ARS | J5: Priority | K5: PM Used | L5: RM Used | M5: Complexity | N5: Outcome | O5: Action Required
A6: 1 | B6: P195 | C6: LA Tech | D6: Workday Student | E6: Risk Management | F6: 4.27 | G6: 5 | H6: ='SEM Weights'!$D$9 -> 0.38 | I6: =F6*G6*H6 -> 8.113 | J6: =IF(I6>12,"Critical",IF(I6>=6,"High",IF(I6>=3,"Moderate","Low"))) -> High | K6: Yes | L6: Yes | M6: High | N6: Delayed | O6: Active mitigation planning required; include in formal risk register
A7: 2 | B7: P053 | C7: RPI | D7: Network services | E7: Risk Management | F7: 4.64 | G7: 4.25 | H7: ='SEM Weights'!$D$9 -> 0.38 | I7: =F7*G7*H7 -> 7.4936 | J7: =IF(I7>12,"Critical",IF(I7>=6,"High",IF(I7>=3,"Moderate","Low"))) -> High | K7: Yes | L7: Yes | M7: High | N7: Delayed | O7: Active mitigation planning required; include in formal risk register
A8: 3 | B8: P107 | C8: RPI | D8: Inventions and patents | E8: Risk Management | F8: 3.91 | G8: 5 | H8: ='SEM Weights'!$D$9 -> 0.38 | I8: =F8*G8*H8 -> 7.429 | J8: =IF(I8>12,"Critical",IF(I8>=6,"High",IF(I8>=3,"Moderate","Low"))) -> High | K8: No | L8: No | M8: High | N8: Delayed | O8: Active mitigation planning required; include in formal risk register
A9: 4 | B9: P155 | C9: RPI | D9: Email Spam filter | E9: Risk Management | F9: 4.27 | G9: 4.5 | H9: ='SEM Weights'!$D$9 -> 0.38 | I9: =F9*G9*H9 -> 7.3017 | J9: =IF(I9>12,"Critical",IF(I9>=6,"High",IF(I9>=3,"Moderate","Low"))) -> High | K9: Yes | L9: Yes | M9: High | N9: Delayed | O9: Active mitigation planning required; include in formal risk register
A10: 5 | B10: P049 | C10: RPI | D10: Backups | E10: Risk Management | F10: 3.91 | G10: 4.75 | H10: ='SEM Weights'!$D$9 -> 0.38 | I10: =F10*G10*H10 -> 7.05755 | J10: =IF(I10>12,"Critical",IF(I10>=6,"High",IF(I10>=3,"Moderate","Low"))) -> High | K10: Yes | L10: Yes | M10: High | N10: Delayed | O10: Active mitigation planning required; include in formal risk register
A11: 6 | B11: P010 | C11: RPI | D11: Parking Management System | E11: Risk Management | F11: 4.27 | G11: 4.25 | H11: ='SEM Weights'!$D$9 -> 0.38 | I11: =F11*G11*H11 -> 6.89605 | J11: =IF(I11>12,"Critical",IF(I11>=6,"High",IF(I11>=3,"Moderate","Low"))) -> High | K11: No | L11: No | M11: High | N11: Delayed | O11: Active mitigation planning required; include in formal risk register
A12: 7 | B12: P076 | C12: RPI | D12: Payment processing Software (check print | E12: Risk Management | F12: 3.55 | G12: 5 | H12: ='SEM Weights'!$D$9 -> 0.38 | I12: =F12*G12*H12 -> 6.745 | J12: =IF(I12>12,"Critical",IF(I12>=6,"High",IF(I12>=3,"Moderate","Low"))) -> High | K12: Yes | L12: Yes | M12: High | N12: Delayed | O12: Active mitigation planning required; include in formal risk register
A13: 8 | B13: P122 | C13: RPI | D13: Package Tracking System | E13: Risk Management | F13: 3.55 | G13: 5 | H13: ='SEM Weights'!$D$9 -> 0.38 | I13: =F13*G13*H13 -> 6.745 | J13: =IF(I13>12,"Critical",IF(I13>=6,"High",IF(I13>=3,"Moderate","Low"))) -> High | K13: Yes | L13: Yes | M13: High | N13: Delayed | O13: Active mitigation planning required; include in formal risk register
A14: 9 | B14: P136 | C14: RPI | D14: Interlibrary loan and document delivery | E14: Risk Management | F14: 3.55 | G14: 5 | H14: ='SEM Weights'!$D$9 -> 0.38 | I14: =F14*G14*H14 -> 6.745 | J14: =IF(I14>12,"Critical",IF(I14>=6,"High",IF(I14>=3,"Moderate","Low"))) -> High | K14: No | L14: Yes | M14: High | N14: Delayed | O14: Active mitigation planning required; include in formal risk register
A15: 10 | B15: P142 | C15: RPI | D15: Data Warehouse Business Intelligence and | E15: Risk Management | F15: 3.91 | G15: 4.5 | H15: ='SEM Weights'!$D$9 -> 0.38 | I15: =F15*G15*H15 -> 6.6861 | J15: =IF(I15>12,"Critical",IF(I15>=6,"High",IF(I15>=3,"Moderate","Low"))) -> High | K15: Yes | L15: Yes | M15: High | N15: Delayed | O15: Active mitigation planning required; include in formal risk register
A16: 11 | B16: P110 | C16: RPI | D16: Intellectual Property | E16: Risk Management | F16: 5 | G16: 3.5 | H16: ='SEM Weights'!$D$9 -> 0.38 | I16: =F16*G16*H16 -> 6.65 | J16: =IF(I16>12,"Critical",IF(I16>=6,"High",IF(I16>=3,"Moderate","Low"))) -> High | K16: Yes | L16: Yes | M16: Medium | N16: Failed | O16: Active mitigation planning required; include in formal risk register
A17: 12 | B17: P041 | C17: RPI | D17: Wireless network management | E17: Risk Management | F17: 3.55 | G17: 4.75 | H17: ='SEM Weights'!$D$9 -> 0.38 | I17: =F17*G17*H17 -> 6.40775 | J17: =IF(I17>12,"Critical",IF(I17>=6,"High",IF(I17>=3,"Moderate","Low"))) -> High | K17: Yes | L17: Yes | M17: High | N17: Delayed | O17: Active mitigation planning required; include in formal risk register
... A35: 30 | B35: P091 | C35: RPI | D35: because Microsoft Live is not effective | E35: Organizational Readiness | F35: 2.82 | G35: 4.75 | H35: ='SEM Weights'!$D$9 -> 0.38 | I35: =F35*G35*H35 -> 5.0901 | J35: =IF(I35>12,"Critical",IF(I35>=6,"High",IF(I35>=3,"Moderate","Low"))) -> Moderate | K35: No | L35: Yes | M35: High | N35: Delayed | O35: Periodic monitoring; develop contingency plan at next milestone

Sheet Formula Reference
A2: ARS Formula Reference & Methodology Documentation
B5: THE FORMULA | C5: ARS = P × I × β
B7: VARIABLE | C7: DEFINITION
B8: P — Probability | C8: Likelihood of risk occurring (1–5). In this study derived from Risk_Score_Normalized (0–100) scaled to 1–5.
B9: I — Impact | C9: Severity of consequences (1–5). Derived from project Complexity and risk weighting components, scaled to 1–5.
B10: β — SEM Weight | C10: Standardized path coefficient from IBM AMOS. β = 0.53 for RM→IS (placeholder; update after AMOS run). Reflects empirically-validated causal importance of construct on Implementation Success.
B11: ARS | C11: Adjusted Risk Score. Higher ARS = higher institutional priority. Grounded in SEM causal theory rather than expert judgment alone.
B13: PRIORITY TIERS | C13: CLASSIFICATION & DATASET COUNTS
B14: ARS > 12.0 | C14: CRITICAL — Immediate mitigation. Count in dataset: 0 (0.0%)
B15: ARS 6.0–12.0 | C15: HIGH — Active mitigation required. Count in dataset: 28 (14.4%)
B16: ARS 3.0–6.0 | C16: MODERATE — Periodic monitoring. Count in dataset: 93 (47.7%)
B17: ARS < 3.0 | C17: LOW — Accept with monitoring. Count in dataset: 74 (37.9%)
B19: RM INDICATOR DERIVATION | C19: HOW RM1, RM2, RM3 ARE DERIVED FROM ARS
B20: RM1 — Identification
B21: RM2 — Assessment
B22: RM3 — Mitigation
B24: KEY CITATIONS | C24: ARS formula: Chapter 3 Section 3.5.4. β weights: Chapter 4 Table 4.9. RM derivation: Dataset v2 Conversion Documentation. PMI PMBOK 7th Ed. ISO 31000. Selvakumar et al. (2024). de Bakker et al. (2010). Goswami (2024).
